{
  "generated_utc": "2026-06-27T19:13:33Z",
  "top": [
    {
      "lon": 26.25,
      "lat": 44.25,
      "type": "early_warning",
      "escalation": 100.0,
      "cell_deg": 0.5,
      "neighbor_active": 0,
      "recent": 335.077,
      "baseline": 940.147,
      "ratio": 0.356,
      "src_mix": 2,
      "zone": null,
      "zone_mult": 1.0,
      "src_recent": {
        "GDELT": 10,
        "GDELT_DOC": 252,
        "DIRECT_FEED": 0,
        "USGS": 0,
        "GDACS": 0
      },
      "place": "Giurgiu, Romania"
    },
    {
      "lon": 25.25,
      "lat": 54.75,
      "type": "early_warning",
      "escalation": 72.6,
      "cell_deg": 0.5,
      "neighbor_active": 0,
      "recent": 191.135,
      "baseline": 476.47,
      "ratio": 0.401,
      "src_mix": 2,
      "zone": "LT–BY perem (tág)",
      "zone_mult": 1.15,
      "src_recent": {
        "GDELT": 5,
        "GDELT_DOC": 146,
        "DIRECT_FEED": 0,
        "USGS": 0,
        "GDACS": 0
      },
      "place": "Vilnius County, Lithuania"
    },
    {
      "lon": 14.25,
      "lat": 50.25,
      "type": "early_warning",
      "escalation": 71.9,
      "cell_deg": 0.5,
      "neighbor_active": 0,
      "recent": 304.322,
      "baseline": 1115.383,
      "ratio": 0.273,
      "src_mix": 2,
      "zone": null,
      "zone_mult": 1.0,
      "src_recent": {
        "GDELT": 15,
        "GDELT_DOC": 227,
        "DIRECT_FEED": 0,
        "USGS": 0,
        "GDACS": 0
      },
      "place": "SO ORP Kralupy nad Vltavou, Czechia"
    },
    {
      "lon": 20.25,
      "lat": 52.25,
      "type": "early_warning",
      "escalation": 21.6,
      "cell_deg": 0.5,
      "neighbor_active": 0,
      "recent": 86.185,
      "baseline": 270.894,
      "ratio": 0.318,
      "src_mix": 1,
      "zone": null,
      "zone_mult": 1.0,
      "src_recent": {
        "GDELT": 63,
        "GDELT_DOC": 0,
        "DIRECT_FEED": 0,
        "USGS": 0,
        "GDACS": 0
      },
      "place": "Sochaczew County, Poland"
    },
    {
      "lon": 19.25,
      "lat": 47.75,
      "type": "early_warning",
      "escalation": 18.6,
      "cell_deg": 0.5,
      "neighbor_active": 0,
      "recent": 78.34,
      "baseline": 285.534,
      "ratio": 0.275,
      "src_mix": 2,
      "zone": null,
      "zone_mult": 1.0,
      "src_recent": {
        "GDELT": 22,
        "GDELT_DOC": 0,
        "DIRECT_FEED": 36,
        "USGS": 0,
        "GDACS": 0
      },
      "place": "Pest, Hungary"
    },
    {
      "lon": 24.25,
      "lat": 56.75,
      "type": "early_warning",
      "escalation": 18.1,
      "cell_deg": 0.5,
      "neighbor_active": 0,
      "recent": 60.077,
      "baseline": 167.072,
      "ratio": 0.359,
      "src_mix": 2,
      "zone": null,
      "zone_mult": 1.0,
      "src_recent": {
        "GDELT": 3,
        "GDELT_DOC": 0,
        "DIRECT_FEED": 38,
        "USGS": 0,
        "GDACS": 0
      },
      "place": "Ķekavas novads, Latvia"
    },
    {
      "lon": 15.25,
      "lat": 49.75,
      "type": "early_warning",
      "escalation": 14.6,
      "cell_deg": 0.5,
      "neighbor_active": 0,
      "recent": 37.352,
      "baseline": 68.723,
      "ratio": 0.539,
      "src_mix": 1,
      "zone": null,
      "zone_mult": 1.0,
      "src_recent": {
        "GDELT": 28,
        "GDELT_DOC": 0,
        "DIRECT_FEED": 0,
        "USGS": 0,
        "GDACS": 0
      },
      "place": "Vysočina Region, Czechia"
    },
    {
      "lon": 25.25,
      "lat": 46.25,
      "type": "early_warning",
      "escalation": 12.9,
      "cell_deg": 0.5,
      "neighbor_active": 0,
      "recent": 52.556,
      "baseline": 188.235,
      "ratio": 0.28,
      "src_mix": 1,
      "zone": "RO–UA perem (tág)",
      "zone_mult": 1.1,
      "src_recent": {
        "GDELT": 39,
        "GDELT_DOC": 0,
        "DIRECT_FEED": 0,
        "USGS": 0,
        "GDACS": 0
      },
      "place": "Harghita, Romania"
    },
    {
      "lon": 19.25,
      "lat": 52.25,
      "type": "early_warning",
      "escalation": 10.0,
      "cell_deg": 0.5,
      "neighbor_active": 0,
      "recent": 19.251,
      "baseline": 23.927,
      "ratio": 0.777,
      "src_mix": 1,
      "zone": null,
      "zone_mult": 1.0,
      "src_recent": {
        "GDELT": 0,
        "GDELT_DOC": 0,
        "DIRECT_FEED": 13,
        "USGS": 0,
        "GDACS": 0
      },
      "place": "Kutno County, Poland"
    },
    {
      "lon": 25.25,
      "lat": 57.25,
      "type": "early_warning",
      "escalation": 9.0,
      "cell_deg": 0.5,
      "neighbor_active": 0,
      "recent": 19.323,
      "baseline": 27.945,
      "ratio": 0.673,
      "src_mix": 1,
      "zone": null,
      "zone_mult": 1.0,
      "src_recent": {
        "GDELT": 14,
        "GDELT_DOC": 0,
        "DIRECT_FEED": 0,
        "USGS": 0,
        "GDACS": 0
      },
      "place": "Cēsu novads, Latvia"
    }
  ]
}