{
  "generated_utc": "2026-04-28T19:50:43Z",
  "top": [
    {
      "lon": 14.25,
      "lat": 50.25,
      "type": "early_warning",
      "escalation": 100.0,
      "cell_deg": 0.5,
      "neighbor_active": 0,
      "recent": 562.631,
      "baseline": 1573.68,
      "ratio": 0.358,
      "src_mix": 2,
      "zone": null,
      "zone_mult": 1.0,
      "src_recent": {
        "GDELT": 35,
        "GDELT_DOC": 407,
        "DIRECT_FEED": 0,
        "USGS": 0,
        "GDACS": 0
      },
      "place": "SO ORP Kralupy nad Vltavou, Czechia"
    },
    {
      "lon": 26.25,
      "lat": 44.25,
      "type": "early_warning",
      "escalation": 91.9,
      "cell_deg": 0.5,
      "neighbor_active": 0,
      "recent": 503.933,
      "baseline": 1486.37,
      "ratio": 0.339,
      "src_mix": 3,
      "zone": null,
      "zone_mult": 1.0,
      "src_recent": {
        "GDELT": 31,
        "GDELT_DOC": 363,
        "DIRECT_FEED": 2,
        "USGS": 0,
        "GDACS": 0
      },
      "place": "Giurgiu, Romania"
    },
    {
      "lon": 25.25,
      "lat": 54.75,
      "type": "early_warning",
      "escalation": 89.0,
      "cell_deg": 0.5,
      "neighbor_active": 0,
      "recent": 399.927,
      "baseline": 1012.118,
      "ratio": 0.395,
      "src_mix": 2,
      "zone": "LT–BY perem (tág)",
      "zone_mult": 1.15,
      "src_recent": {
        "GDELT": 16,
        "GDELT_DOC": 300,
        "DIRECT_FEED": 0,
        "USGS": 0,
        "GDACS": 0
      },
      "place": "Vilnius County, Lithuania"
    },
    {
      "lon": 25.25,
      "lat": 46.25,
      "type": "early_warning",
      "escalation": 25.6,
      "cell_deg": 0.5,
      "neighbor_active": 0,
      "recent": 83.33,
      "baseline": 122.065,
      "ratio": 0.678,
      "src_mix": 1,
      "zone": "RO–UA perem (tág)",
      "zone_mult": 1.1,
      "src_recent": {
        "GDELT": 62,
        "GDELT_DOC": 0,
        "DIRECT_FEED": 0,
        "USGS": 0,
        "GDACS": 0
      },
      "place": "Harghita, Romania"
    },
    {
      "lon": 19.25,
      "lat": 47.75,
      "type": "early_warning",
      "escalation": 24.3,
      "cell_deg": 0.5,
      "neighbor_active": 0,
      "recent": 139.066,
      "baseline": 396.818,
      "ratio": 0.35,
      "src_mix": 2,
      "zone": null,
      "zone_mult": 1.0,
      "src_recent": {
        "GDELT": 32,
        "GDELT_DOC": 0,
        "DIRECT_FEED": 69,
        "USGS": 0,
        "GDACS": 0
      },
      "place": "Pest, Hungary"
    },
    {
      "lon": 24.25,
      "lat": 56.75,
      "type": "early_warning",
      "escalation": 18.8,
      "cell_deg": 0.5,
      "neighbor_active": 0,
      "recent": 77.739,
      "baseline": 150.432,
      "ratio": 0.515,
      "src_mix": 2,
      "zone": null,
      "zone_mult": 1.0,
      "src_recent": {
        "GDELT": 8,
        "GDELT_DOC": 0,
        "DIRECT_FEED": 47,
        "USGS": 0,
        "GDACS": 0
      },
      "place": "Ķekavas novads, Latvia"
    },
    {
      "lon": 21.25,
      "lat": 52.25,
      "type": "early_warning",
      "escalation": 16.1,
      "cell_deg": 0.5,
      "neighbor_active": 0,
      "recent": 54.085,
      "baseline": 72.706,
      "ratio": 0.736,
      "src_mix": 1,
      "zone": null,
      "zone_mult": 1.0,
      "src_recent": {
        "GDELT": 40,
        "GDELT_DOC": 0,
        "DIRECT_FEED": 0,
        "USGS": 0,
        "GDACS": 0
      },
      "place": "Warsaw, Poland"
    },
    {
      "lon": 15.25,
      "lat": 49.75,
      "type": "early_warning",
      "escalation": 14.5,
      "cell_deg": 0.5,
      "neighbor_active": 0,
      "recent": 49.4,
      "baseline": 67.33,
      "ratio": 0.725,
      "src_mix": 1,
      "zone": null,
      "zone_mult": 1.0,
      "src_recent": {
        "GDELT": 37,
        "GDELT_DOC": 0,
        "DIRECT_FEED": 0,
        "USGS": 0,
        "GDACS": 0
      },
      "place": "Vysočina Region, Czechia"
    },
    {
      "lon": 20.25,
      "lat": 52.25,
      "type": "early_warning",
      "escalation": 12.6,
      "cell_deg": 0.5,
      "neighbor_active": 0,
      "recent": 81.214,
      "baseline": 242.575,
      "ratio": 0.335,
      "src_mix": 1,
      "zone": null,
      "zone_mult": 1.0,
      "src_recent": {
        "GDELT": 60,
        "GDELT_DOC": 0,
        "DIRECT_FEED": 0,
        "USGS": 0,
        "GDACS": 0
      },
      "place": "Sochaczew County, Poland"
    },
    {
      "lon": 20.25,
      "lat": 47.25,
      "type": "early_warning",
      "escalation": 8.7,
      "cell_deg": 0.5,
      "neighbor_active": 0,
      "recent": 73.752,
      "baseline": 301.928,
      "ratio": 0.245,
      "src_mix": 1,
      "zone": null,
      "zone_mult": 1.0,
      "src_recent": {
        "GDELT": 55,
        "GDELT_DOC": 0,
        "DIRECT_FEED": 0,
        "USGS": 0,
        "GDACS": 0
      },
      "place": "Jász-Nagykun-Szolnok, Hungary"
    }
  ]
}