{
  "generated_utc": "2026-03-19T13:11:31Z",
  "top": [
    {
      "lon": 26.25,
      "lat": 44.25,
      "type": "early_warning",
      "escalation": 100.0,
      "cell_deg": 0.5,
      "neighbor_active": 0,
      "recent": 552.255,
      "baseline": 1076.468,
      "ratio": 0.513,
      "src_mix": 2,
      "zone": null,
      "zone_mult": 1.0,
      "src_recent": {
        "GDELT": 15,
        "GDELT_DOC": 416,
        "DIRECT_FEED": 0,
        "USGS": 0,
        "GDACS": 0
      },
      "place": "Giurgiu, Romania"
    },
    {
      "lon": 14.25,
      "lat": 50.25,
      "type": "early_warning",
      "escalation": 89.2,
      "cell_deg": 0.5,
      "neighbor_active": 0,
      "recent": 551.633,
      "baseline": 1233.37,
      "ratio": 0.447,
      "src_mix": 2,
      "zone": null,
      "zone_mult": 1.0,
      "src_recent": {
        "GDELT": 10,
        "GDELT_DOC": 424,
        "DIRECT_FEED": 0,
        "USGS": 0,
        "GDACS": 0
      },
      "place": "SO ORP Kralupy nad Vltavou, Czechia"
    },
    {
      "lon": 25.25,
      "lat": 54.75,
      "type": "early_warning",
      "escalation": 46.6,
      "cell_deg": 0.5,
      "neighbor_active": 0,
      "recent": 294.01,
      "baseline": 794.408,
      "ratio": 0.37,
      "src_mix": 2,
      "zone": "LT–BY perem (tág)",
      "zone_mult": 1.15,
      "src_recent": {
        "GDELT": 9,
        "GDELT_DOC": 224,
        "DIRECT_FEED": 0,
        "USGS": 0,
        "GDACS": 0
      },
      "place": "Vilnius County, Lithuania"
    },
    {
      "lon": 19.25,
      "lat": 47.75,
      "type": "early_warning",
      "escalation": 30.5,
      "cell_deg": 0.5,
      "neighbor_active": 0,
      "recent": 173.581,
      "baseline": 350.83,
      "ratio": 0.494,
      "src_mix": 2,
      "zone": null,
      "zone_mult": 1.0,
      "src_recent": {
        "GDELT": 50,
        "GDELT_DOC": 0,
        "DIRECT_FEED": 76,
        "USGS": 0,
        "GDACS": 0
      },
      "place": "Pest, Hungary"
    },
    {
      "lon": 24.25,
      "lat": 56.75,
      "type": "early_warning",
      "escalation": 13.5,
      "cell_deg": 0.5,
      "neighbor_active": 0,
      "recent": 74.521,
      "baseline": 144.116,
      "ratio": 0.515,
      "src_mix": 2,
      "zone": null,
      "zone_mult": 1.0,
      "src_recent": {
        "GDELT": 3,
        "GDELT_DOC": 0,
        "DIRECT_FEED": 48,
        "USGS": 0,
        "GDACS": 0
      },
      "place": "Ķekavas novads, Latvia"
    },
    {
      "lon": 25.25,
      "lat": 46.25,
      "type": "early_warning",
      "escalation": 12.8,
      "cell_deg": 0.5,
      "neighbor_active": 0,
      "recent": 67.512,
      "baseline": 127.067,
      "ratio": 0.529,
      "src_mix": 1,
      "zone": "RO–UA perem (tág)",
      "zone_mult": 1.1,
      "src_recent": {
        "GDELT": 50,
        "GDELT_DOC": 0,
        "DIRECT_FEED": 0,
        "USGS": 0,
        "GDACS": 0
      },
      "place": "Harghita, Romania"
    },
    {
      "lon": 20.25,
      "lat": 52.25,
      "type": "early_warning",
      "escalation": 10.8,
      "cell_deg": 0.5,
      "neighbor_active": 0,
      "recent": 82.077,
      "baseline": 213.429,
      "ratio": 0.384,
      "src_mix": 1,
      "zone": null,
      "zone_mult": 1.0,
      "src_recent": {
        "GDELT": 60,
        "GDELT_DOC": 0,
        "DIRECT_FEED": 0,
        "USGS": 0,
        "GDACS": 0
      },
      "place": "Sochaczew County, Poland"
    },
    {
      "lon": 15.25,
      "lat": 49.75,
      "type": "early_warning",
      "escalation": 9.0,
      "cell_deg": 0.5,
      "neighbor_active": 0,
      "recent": 40.04,
      "baseline": 53.29,
      "ratio": 0.74,
      "src_mix": 1,
      "zone": null,
      "zone_mult": 1.0,
      "src_recent": {
        "GDELT": 29,
        "GDELT_DOC": 0,
        "DIRECT_FEED": 0,
        "USGS": 0,
        "GDACS": 0
      },
      "place": "Vysočina Region, Czechia"
    },
    {
      "lon": 22.25,
      "lat": 48.25,
      "type": "early_warning",
      "escalation": 9.0,
      "cell_deg": 0.5,
      "neighbor_active": 0,
      "recent": 28.928,
      "baseline": 28.15,
      "ratio": 0.992,
      "src_mix": 1,
      "zone": "HU–UA perem (tág)",
      "zone_mult": 1.12,
      "src_recent": {
        "GDELT": 0,
        "GDELT_DOC": 0,
        "DIRECT_FEED": 16,
        "USGS": 0,
        "GDACS": 0
      },
      "place": "Szabolcs-Szatmár-Bereg, Hungary"
    },
    {
      "lon": 20.25,
      "lat": 47.25,
      "type": "early_warning",
      "escalation": 6.1,
      "cell_deg": 0.5,
      "neighbor_active": 0,
      "recent": 58.141,
      "baseline": 195.848,
      "ratio": 0.297,
      "src_mix": 1,
      "zone": null,
      "zone_mult": 1.0,
      "src_recent": {
        "GDELT": 42,
        "GDELT_DOC": 0,
        "DIRECT_FEED": 0,
        "USGS": 0,
        "GDACS": 0
      },
      "place": "Jász-Nagykun-Szolnok, Hungary"
    }
  ]
}