{
  "generated_utc": "2026-02-27T07:13:56Z",
  "headline": "Közép–Kelet Európa biztonsági helyzet – napi kivonat",
  "bullets": [
    "Legerősebb góc: Sochaczew County, Poland 🔺 (rácspont 52.25, 20.25; score 19.65; 7 napos változás: +367%).",
    "Trend: emelkedő (+392%) az előző 7 naphoz képest.",
    "Forráskép: GDELT 0, USGS 2, GDACS 0.",
    "Megjegyzés: automatikus OSINT-kivonat; a linkelt források kézi ellenőrzése javasolt."
  ],
  "alert": {
    "level": "high",
    "title": "Emelkedő feszültség",
    "text": "Erősödő hotspot: Sochaczew County, Poland (+367%)."
  },
  "stats": {
    "score_last7": 273.755,
    "score_prev7": 55.663,
    "change_pct": 391.81
  }
}