{
  "generated_utc": "2026-07-12T19:01:40Z",
  "headline": "Közép–Kelet Európa biztonsági helyzet – napi kivonat",
  "bullets": [
    "Az infrastruktúra-közelségi modul 685 friss kapcsolatot azonosított események és kritikus objektumok között; ebből 404 magas vagy kritikus szintű.",
    "CRITICAL infrastruktúra-jelzés: Prague Internet Exchange / NIX.CZ (Czechia) – 0.8 km-re ettől: Alles zur WM 2026 - Borussia Dortmund - Forum | Seite 368.",
    "CRITICAL infrastruktúra-jelzés: Prague Internet Exchange / NIX.CZ (Czechia) – 0.8 km-re ettől: Ultima postare a pilotului Adrian Rus – Sinner , mort în accidentul din Cehia . Avea doar 30 de ani.",
    "CRITICAL infrastruktúra-jelzés: Prague Internet Exchange / NIX.CZ (Czechia) – 0.8 km-re ettől: Cinturão Verde : natureza onde antes era a faixa da morte.",
    "Legerősebb góc: SO ORP Kralupy nad Vltavou, Czechia 🔺 (rácspont 50.25, 14.25; score 781.78; 7 napos változás: +11264%).",
    "Trend: emelkedő (+1510%) az előző 7 naphoz képest.",
    "Forráskép: GDELT 0, GDELT linked 2883, GDELT DOC 2801, direkt feed 327, USGS 1, GDACS 1.",
    "Trusted RSS forrásokból releváns sajtóanyag: 200 db.",
    "Megjegyzés: automatikus OSINT-kivonat; a linkelt források kézi ellenőrzése javasolt."
  ],
  "alert": {
    "level": "high",
    "title": "Emelkedő feszültség",
    "text": "Erősödő hotspot: SO ORP Kralupy nad Vltavou, Czechia (+11264%)."
  },
  "stats": {
    "score_last7": 2616.71,
    "score_prev7": 162.506,
    "change_pct": 1510.23
  },
  "rss_count": 200,
  "local_infrastructure": {
    "last_24h_local_events": 0,
    "last_24h_proximity_matches": 685,
    "top_proximity": [
      {
        "id": "56d79f3a5dd5e925",
        "level": "critical",
        "score": 97.1,
        "distance_km": 1.45,
        "event": {
          "id": "dbbe6d806bb04ee3",
          "title": "Tallinn, Harjumaa, Estonia",
          "category": "security_politics",
          "source": "GDELT",
          "time": "2026-07-12T00:00:00Z",
          "url": "https://www.eurasiareview.com/11072026-marxism-succeeded-in-russia-because-its-denial-of-freedom-matched-russian-national-character-oped/",
          "lat": 59.4339,
          "lon": 24.7281,
          "source_file": "gdelt_linked.geojson"
        },
        "infrastructure": {
          "id": "ee-digital-tallinn-cyber-hub",
          "name": "Tallinn Cyber and Digital Infrastructure Hub",
          "country": "Estonia",
          "city": "Tallinn",
          "category": "digital",
          "subtype": "cyber_digital_government_hub",
          "criticality": 10.0,
          "operator": "Multiple operators / public sector",
          "lat": 59.437,
          "lon": 24.753,
          "source_file": "infra_digital.json"
        }
      },
      {
        "id": "fb09ad62b2bca182",
        "level": "critical",
        "score": 97.1,
        "distance_km": 1.45,
        "event": {
          "id": "57c34a592c612285",
          "title": "Tallinn, Harjumaa, Estonia",
          "category": "other",
          "source": "GDELT",
          "time": "2026-07-12T00:00:00Z",
          "url": "https://www.eurasiareview.com/12072026-new-ukrainian-study-says-eight-out-of-ten-russian-regions-capable-of-rapidly-becoming-independent-countries-once-moscow-collapses-oped/",
          "lat": 59.4339,
          "lon": 24.7281,
          "source_file": "gdelt_linked.geojson"
        },
        "infrastructure": {
          "id": "ee-digital-tallinn-cyber-hub",
          "name": "Tallinn Cyber and Digital Infrastructure Hub",
          "country": "Estonia",
          "city": "Tallinn",
          "category": "digital",
          "subtype": "cyber_digital_government_hub",
          "criticality": 10.0,
          "operator": "Multiple operators / public sector",
          "lat": 59.437,
          "lon": 24.753,
          "source_file": "infra_digital.json"
        }
      },
      {
        "id": "9f64650ec27d2275",
        "level": "critical",
        "score": 88.57,
        "distance_km": 0.8,
        "event": {
          "id": "e5af03f15b6f571c",
          "title": "Alles zur WM 2026 - Borussia Dortmund - Forum | Seite 368",
          "category": "other",
          "source": "GDELT_DOC",
          "time": "2026-07-12T18:30:00Z",
          "url": "https://www.transfermarkt.at/alles-zur-wm-2026/thread/forum/12/thread_id/806289/page/368",
          "lat": 50.08,
          "lon": 14.43,
          "source_file": "gdelt_crossborder.geojson"
        },
        "infrastructure": {
          "id": "cz-digital-prague-ixp",
          "name": "Prague Internet Exchange / NIX.CZ",
          "country": "Czechia",
          "city": "Prague",
          "category": "digital",
          "subtype": "internet_exchange",
          "criticality": 9.0,
          "operator": "NIX.CZ",
          "lat": 50.075,
          "lon": 14.438,
          "source_file": "infra_digital.json"
        }
      },
      {
        "id": "90370b5e3d53057a",
        "level": "critical",
        "score": 88.57,
        "distance_km": 0.8,
        "event": {
          "id": "1abb7d5c8d92081d",
          "title": "Ultima postare a pilotului Adrian Rus – Sinner , mort în accidentul din Cehia . Avea doar 30 de ani",
          "category": "other",
          "source": "GDELT_DOC",
          "time": "2026-07-12T18:30:00Z",
          "url": "https://www.ziarulprofit.ro/ultima-postare-a-pilotului-adrian-rus-sinner-mort-in-accidentul-din-cehia-avea-doar-30-de-ani/",
          "lat": 50.08,
          "lon": 14.43,
          "source_file": "gdelt_crossborder.geojson"
        },
        "infrastructure": {
          "id": "cz-digital-prague-ixp",
          "name": "Prague Internet Exchange / NIX.CZ",
          "country": "Czechia",
          "city": "Prague",
          "category": "digital",
          "subtype": "internet_exchange",
          "criticality": 9.0,
          "operator": "NIX.CZ",
          "lat": 50.075,
          "lon": 14.438,
          "source_file": "infra_digital.json"
        }
      },
      {
        "id": "cb82ca15d375f91a",
        "level": "critical",
        "score": 88.57,
        "distance_km": 0.8,
        "event": {
          "id": "5763c572f055d38c",
          "title": "Cinturão Verde : natureza onde antes era a faixa da morte",
          "category": "other",
          "source": "GDELT_DOC",
          "time": "2026-07-12T17:30:00Z",
          "url": "https://www.dw.com/pt-br/cintur%C3%A3o-verde-ocupa-antiga-faixa-da-morte-entre-as-duas-alemanhas/a-77925381",
          "lat": 50.08,
          "lon": 14.43,
          "source_file": "gdelt_crossborder.geojson"
        },
        "infrastructure": {
          "id": "cz-digital-prague-ixp",
          "name": "Prague Internet Exchange / NIX.CZ",
          "country": "Czechia",
          "city": "Prague",
          "category": "digital",
          "subtype": "internet_exchange",
          "criticality": 9.0,
          "operator": "NIX.CZ",
          "lat": 50.075,
          "lon": 14.438,
          "source_file": "infra_digital.json"
        }
      },
      {
        "id": "bdc28a1ae901fddb",
        "level": "critical",
        "score": 88.57,
        "distance_km": 0.8,
        "event": {
          "id": "d7dcd84a9e8cf75a",
          "title": "LITERÁRNÍ ESA : Mám celou bednu příběhů svých předků , říká Monika Czernin",
          "category": "other",
          "source": "GDELT_DOC",
          "time": "2026-07-12T17:30:00Z",
          "url": "https://www.novinky.cz/clanek/kultura-knihy-literarni-esa-mam-celou-bednu-pribehu-svych-predku-rika-monika-czernin-40581815",
          "lat": 50.08,
          "lon": 14.43,
          "source_file": "gdelt_crossborder.geojson"
        },
        "infrastructure": {
          "id": "cz-digital-prague-ixp",
          "name": "Prague Internet Exchange / NIX.CZ",
          "country": "Czechia",
          "city": "Prague",
          "category": "digital",
          "subtype": "internet_exchange",
          "criticality": 9.0,
          "operator": "NIX.CZ",
          "lat": 50.075,
          "lon": 14.438,
          "source_file": "infra_digital.json"
        }
      },
      {
        "id": "eaa022f5f453c7a5",
        "level": "critical",
        "score": 88.57,
        "distance_km": 0.8,
        "event": {
          "id": "622819007b804632",
          "title": "Herzl Lived Upstairs . A Palestinian Pizza Shop Lives Below",
          "category": "other",
          "source": "GDELT_DOC",
          "time": "2026-07-12T17:30:00Z",
          "url": "https://themedialine.org/top-stories/herzl-lived-upstairs-a-palestinian-pizza-shop-lives-below/",
          "lat": 50.08,
          "lon": 14.43,
          "source_file": "gdelt_crossborder.geojson"
        },
        "infrastructure": {
          "id": "cz-digital-prague-ixp",
          "name": "Prague Internet Exchange / NIX.CZ",
          "country": "Czechia",
          "city": "Prague",
          "category": "digital",
          "subtype": "internet_exchange",
          "criticality": 9.0,
          "operator": "NIX.CZ",
          "lat": 50.075,
          "lon": 14.438,
          "source_file": "infra_digital.json"
        }
      },
      {
        "id": "94786cd5278980ab",
        "level": "critical",
        "score": 88.57,
        "distance_km": 0.8,
        "event": {
          "id": "7af3d96cf5a64b04",
          "title": "У яких країнах Європи живе найбагатша молодь Finance . ua",
          "category": "other",
          "source": "GDELT_DOC",
          "time": "2026-07-12T17:15:00Z",
          "url": "https://news.finance.ua/ua/u-yakyh-krainah-yevropy-zhyve-naybahatsha-molod",
          "lat": 50.08,
          "lon": 14.43,
          "source_file": "gdelt_crossborder.geojson"
        },
        "infrastructure": {
          "id": "cz-digital-prague-ixp",
          "name": "Prague Internet Exchange / NIX.CZ",
          "country": "Czechia",
          "city": "Prague",
          "category": "digital",
          "subtype": "internet_exchange",
          "criticality": 9.0,
          "operator": "NIX.CZ",
          "lat": 50.075,
          "lon": 14.438,
          "source_file": "infra_digital.json"
        }
      },
      {
        "id": "31b7b908c26b7ba4",
        "level": "critical",
        "score": 88.57,
        "distance_km": 0.8,
        "event": {
          "id": "50b158d09533b4ba",
          "title": "Štefan Hríb : Klausova a Mečiarova zvrchovanosť , Pavlova a Čaputovej Pohoda ? | Názory | . týždeň",
          "category": "other",
          "source": "GDELT_DOC",
          "time": "2026-07-12T17:00:00Z",
          "url": "https://www.tyzden.sk/nazory/137053/stefan-hrib-klausova-a-meciarova-zvrchovanost-pavlova-a-caputovej-pohoda/",
          "lat": 50.08,
          "lon": 14.43,
          "source_file": "gdelt_crossborder.geojson"
        },
        "infrastructure": {
          "id": "cz-digital-prague-ixp",
          "name": "Prague Internet Exchange / NIX.CZ",
          "country": "Czechia",
          "city": "Prague",
          "category": "digital",
          "subtype": "internet_exchange",
          "criticality": 9.0,
          "operator": "NIX.CZ",
          "lat": 50.075,
          "lon": 14.438,
          "source_file": "infra_digital.json"
        }
      },
      {
        "id": "899903aca41025bf",
        "level": "critical",
        "score": 88.57,
        "distance_km": 0.8,
        "event": {
          "id": "19f4b598be0e47eb",
          "title": "Eine überfällige Lehre aus den vergangenen Krisenjahren",
          "category": "infrastructure",
          "source": "GDELT_DOC",
          "time": "2026-07-12T17:00:00Z",
          "url": "https://www.presseportal.de/pm/122668/6312882",
          "lat": 50.08,
          "lon": 14.43,
          "source_file": "gdelt_crossborder.geojson"
        },
        "infrastructure": {
          "id": "cz-digital-prague-ixp",
          "name": "Prague Internet Exchange / NIX.CZ",
          "country": "Czechia",
          "city": "Prague",
          "category": "digital",
          "subtype": "internet_exchange",
          "criticality": 9.0,
          "operator": "NIX.CZ",
          "lat": 50.075,
          "lon": 14.438,
          "source_file": "infra_digital.json"
        }
      }
    ]
  }
}