{
  "generated_utc": "2026-04-15T13:29:29Z",
  "headline": "Közép–Kelet Európa biztonsági helyzet – napi kivonat",
  "bullets": [
    "Legerősebb góc: SO ORP Kralupy nad Vltavou, Czechia 🔺 (rácspont 50.25, 14.25; score 837.35; 7 napos változás: +15430%).",
    "Trend: emelkedő (+1735%) az előző 7 naphoz képest.",
    "Forráskép: GDELT 0, GDELT linked 3761, GDELT DOC 3316, direkt feed 539, USGS 0, GDACS 0.",
    "Trusted RSS forrásokból releváns sajtóanyag: 200 db.",
    "Megjegyzés: automatikus OSINT-kivonat; a linkelt források kézi ellenőrzése javasolt."
  ],
  "alert": {
    "level": "high",
    "title": "Emelkedő feszültség",
    "text": "Erősödő hotspot: SO ORP Kralupy nad Vltavou, Czechia (+15430%)."
  },
  "stats": {
    "score_last7": 4018.272,
    "score_prev7": 219.005,
    "change_pct": 1734.79
  },
  "rss_count": 200
}