{
  "generated_utc": "2026-04-15T07:51:30Z",
  "headline": "Közép–Kelet Európa biztonsági helyzet – napi kivonat",
  "bullets": [
    "Legerősebb góc: SO ORP Kralupy nad Vltavou, Czechia 🔺 (rácspont 50.25, 14.25; score 826.91; 7 napos változás: +14420%).",
    "Trend: emelkedő (+1627%) az előző 7 naphoz képest.",
    "Forráskép: GDELT 0, GDELT linked 3643, GDELT DOC 3440, direkt feed 537, USGS 0, GDACS 0.",
    "Trusted RSS forrásokból releváns sajtóanyag: 200 db.",
    "Megjegyzés: automatikus OSINT-kivonat; a linkelt források kézi ellenőrzése javasolt."
  ],
  "alert": {
    "level": "high",
    "title": "Emelkedő feszültség",
    "text": "Erősödő hotspot: SO ORP Kralupy nad Vltavou, Czechia (+14420%)."
  },
  "stats": {
    "score_last7": 3993.155,
    "score_prev7": 231.209,
    "change_pct": 1627.07
  },
  "rss_count": 200
}