{
  "generated_utc": "2026-04-28T03:04:42Z",
  "headline": "Közép–Kelet Európa biztonsági helyzet – napi kivonat",
  "bullets": [
    "Legerősebb góc: SO ORP Kralupy nad Vltavou, Czechia 🔺 (rácspont 50.25, 14.25; score 970.58; 7 napos változás: +6360%).",
    "Trend: emelkedő (+1309%) az előző 7 naphoz képest.",
    "Forráskép: GDELT 0, GDELT linked 3417, GDELT DOC 4538, direkt feed 440, USGS 0, GDACS 0.",
    "Trusted RSS forrásokból releváns sajtóanyag: 200 db.",
    "Megjegyzés: automatikus OSINT-kivonat; a linkelt források kézi ellenőrzése javasolt."
  ],
  "alert": {
    "level": "high",
    "title": "Emelkedő feszültség",
    "text": "Erősödő hotspot: SO ORP Kralupy nad Vltavou, Czechia (+6360%)."
  },
  "stats": {
    "score_last7": 3876.831,
    "score_prev7": 275.166,
    "change_pct": 1308.91
  },
  "rss_count": 200
}