{
  "generated_utc": "2026-06-12T02:49:45Z",
  "headline": "Közép–Kelet Európa biztonsági helyzet – napi kivonat",
  "bullets": [
    "Az infrastruktúra-közelségi modul 1210 friss kapcsolatot azonosított események és kritikus objektumok között; ebből 656 magas vagy kritikus szintű.",
    "CRITICAL infrastruktúra-jelzés: Tallinn Cyber and Digital Infrastructure Hub (Estonia) – 1.4 km-re ettől: Tallinn, Harjumaa, Estonia.",
    "CRITICAL infrastruktúra-jelzés: Port of Tallinn (Estonia) – 2.2 km-re ettől: Tallinn, Harjumaa, Estonia.",
    "CRITICAL infrastruktúra-jelzés: Prague Internet Exchange / NIX.CZ (Czechia) – 2.2 km-re ettől: Prague, Praha, Hlavníesto, Czech Republic.",
    "Legerősebb góc: SO ORP Kralupy nad Vltavou, Czechia 🔺 (rácspont 50.25, 14.25; score 559.92; 7 napos változás: +5603%).",
    "Trend: emelkedő (+831%) az előző 7 naphoz képest.",
    "Forráskép: GDELT 0, GDELT linked 2909, GDELT DOC 2374, direkt feed 337, USGS 0, GDACS 0.",
    "Trusted RSS forrásokból releváns sajtóanyag: 200 db.",
    "Megjegyzés: automatikus OSINT-kivonat; a linkelt források kézi ellenőrzése javasolt."
  ],
  "alert": {
    "level": "high",
    "title": "Emelkedő feszültség",
    "text": "Erősödő hotspot: SO ORP Kralupy nad Vltavou, Czechia (+5603%)."
  },
  "stats": {
    "score_last7": 2538.787,
    "score_prev7": 272.761,
    "change_pct": 830.77
  },
  "rss_count": 200,
  "local_infrastructure": {
    "last_24h_local_events": 0,
    "last_24h_proximity_matches": 1210,
    "top_proximity": [
      {
        "id": "bdcf6390339d92ca",
        "level": "critical",
        "score": 97.1,
        "distance_km": 1.45,
        "event": {
          "id": "fa8a83d5308b9c4a",
          "title": "Tallinn, Harjumaa, Estonia",
          "category": "other",
          "source": "GDELT",
          "time": "2026-06-12T00:00:00Z",
          "url": "https://www.worthynews.com/115011-visegrad-nations-meet-as-eu-debates-new-safeguards-for-future-members",
          "lat": 59.4339,
          "lon": 24.7281,
          "source_file": "gdelt_linked.geojson"
        },
        "infrastructure": {
          "id": "ee-digital-tallinn-cyber-hub",
          "name": "Tallinn Cyber and Digital Infrastructure Hub",
          "country": "Estonia",
          "city": "Tallinn",
          "category": "digital",
          "subtype": "cyber_digital_government_hub",
          "criticality": 10.0,
          "operator": "Multiple operators / public sector",
          "lat": 59.437,
          "lon": 24.753,
          "source_file": "infra_digital.json"
        }
      },
      {
        "id": "d6e2d5541dacb1a8",
        "level": "critical",
        "score": 88.57,
        "distance_km": 0.8,
        "event": {
          "id": "a47cfe530d37120b",
          "title": "Osem filmov , tri kontinenty , štyria Modrí anjeli : Súťaž hraných filmov na IFF Art Film",
          "category": "other",
          "source": "GDELT_DOC",
          "time": "2026-06-11T19:45:00Z",
          "url": "https://www.24hod.sk/osem-filmov-tri-kontinenty-styria-modri-anjeli-sutaz-hranych-filmov-na-iff-art-film-cl827057.html",
          "lat": 50.08,
          "lon": 14.43,
          "source_file": "gdelt_crossborder.geojson"
        },
        "infrastructure": {
          "id": "cz-digital-prague-ixp",
          "name": "Prague Internet Exchange / NIX.CZ",
          "country": "Czechia",
          "city": "Prague",
          "category": "digital",
          "subtype": "internet_exchange",
          "criticality": 9.0,
          "operator": "NIX.CZ",
          "lat": 50.075,
          "lon": 14.438,
          "source_file": "infra_digital.json"
        }
      },
      {
        "id": "5778338a2783a71d",
        "level": "critical",
        "score": 88.57,
        "distance_km": 0.8,
        "event": {
          "id": "6966b1db7e28c60d",
          "title": "EU could sleepwalk into conflict with Russia ex - German navy chief",
          "category": "other",
          "source": "GDELT_DOC",
          "time": "2026-06-11T19:00:00Z",
          "url": "http://www.europesun.com/news/279117124/eu-could-sleepwalk-into-conflict-with-russia-ex-german-navy-chief",
          "lat": 50.08,
          "lon": 14.43,
          "source_file": "gdelt_crossborder.geojson"
        },
        "infrastructure": {
          "id": "cz-digital-prague-ixp",
          "name": "Prague Internet Exchange / NIX.CZ",
          "country": "Czechia",
          "city": "Prague",
          "category": "digital",
          "subtype": "internet_exchange",
          "criticality": 9.0,
          "operator": "NIX.CZ",
          "lat": 50.075,
          "lon": 14.438,
          "source_file": "infra_digital.json"
        }
      },
      {
        "id": "0820d978ef2ed2cf",
        "level": "critical",
        "score": 88.57,
        "distance_km": 0.8,
        "event": {
          "id": "0b627250f8b68faf",
          "title": "Křižovatka , nebo jen výjezd ? Slovensko konečně zpřesňuje pravidla přednosti v jízdě",
          "category": "other",
          "source": "GDELT_DOC",
          "time": "2026-06-11T19:00:00Z",
          "url": "https://www.auto.cz/krizovatka-nebo-jen-vyjezd-slovensko-konecne-zpresnuje-pravidla-prednosti-v-jizde-161296",
          "lat": 50.08,
          "lon": 14.43,
          "source_file": "gdelt_crossborder.geojson"
        },
        "infrastructure": {
          "id": "cz-digital-prague-ixp",
          "name": "Prague Internet Exchange / NIX.CZ",
          "country": "Czechia",
          "city": "Prague",
          "category": "digital",
          "subtype": "internet_exchange",
          "criticality": 9.0,
          "operator": "NIX.CZ",
          "lat": 50.075,
          "lon": 14.438,
          "source_file": "infra_digital.json"
        }
      },
      {
        "id": "0debfb1aca5b6700",
        "level": "critical",
        "score": 88.57,
        "distance_km": 0.8,
        "event": {
          "id": "f27a7b1031f71aae",
          "title": "Can the worst World Cup ever find a way to redeem itself ?",
          "category": "other",
          "source": "GDELT_DOC",
          "time": "2026-06-11T18:45:00Z",
          "url": "https://www.salon.com/2026/06/11/can-the-worst-world-cup-ever-find-a-way-to-redeem-itself/",
          "lat": 50.08,
          "lon": 14.43,
          "source_file": "gdelt_crossborder.geojson"
        },
        "infrastructure": {
          "id": "cz-digital-prague-ixp",
          "name": "Prague Internet Exchange / NIX.CZ",
          "country": "Czechia",
          "city": "Prague",
          "category": "digital",
          "subtype": "internet_exchange",
          "criticality": 9.0,
          "operator": "NIX.CZ",
          "lat": 50.075,
          "lon": 14.438,
          "source_file": "infra_digital.json"
        }
      },
      {
        "id": "971ec105a6631df1",
        "level": "critical",
        "score": 88.57,
        "distance_km": 0.8,
        "event": {
          "id": "71c1e0ad2d83cd1d",
          "title": "Saeima noraida rosinājumu likumā liegt dējējvistu turēšanu sprostos",
          "category": "police",
          "source": "GDELT_DOC",
          "time": "2026-06-11T18:30:00Z",
          "url": "https://www.lsm.lv/raksts/zinas/ekonomika/11.06.2026-saeima-noraida-rosinajumu-likuma-liegt-dejejvistu-turesanu-sprostos.a651165/",
          "lat": 50.08,
          "lon": 14.43,
          "source_file": "gdelt_crossborder.geojson"
        },
        "infrastructure": {
          "id": "cz-digital-prague-ixp",
          "name": "Prague Internet Exchange / NIX.CZ",
          "country": "Czechia",
          "city": "Prague",
          "category": "digital",
          "subtype": "internet_exchange",
          "criticality": 9.0,
          "operator": "NIX.CZ",
          "lat": 50.075,
          "lon": 14.438,
          "source_file": "infra_digital.json"
        }
      },
      {
        "id": "ab6b612c115b159f",
        "level": "critical",
        "score": 88.57,
        "distance_km": 0.8,
        "event": {
          "id": "eddf1751111f1b6a",
          "title": "我的文革 （ 163 ） - 博客",
          "category": "other",
          "source": "GDELT_DOC",
          "time": "2026-06-11T18:30:00Z",
          "url": "https://blog.wenxuecity.com/myblog/83351/202606/7746.html",
          "lat": 50.08,
          "lon": 14.43,
          "source_file": "gdelt_crossborder.geojson"
        },
        "infrastructure": {
          "id": "cz-digital-prague-ixp",
          "name": "Prague Internet Exchange / NIX.CZ",
          "country": "Czechia",
          "city": "Prague",
          "category": "digital",
          "subtype": "internet_exchange",
          "criticality": 9.0,
          "operator": "NIX.CZ",
          "lat": 50.075,
          "lon": 14.438,
          "source_file": "infra_digital.json"
        }
      },
      {
        "id": "c166940fbc868b9c",
        "level": "critical",
        "score": 88.57,
        "distance_km": 0.8,
        "event": {
          "id": "23745b46b476f56e",
          "title": "México debuta ante Sudáfrica en el Mundial y busca romper la maldición del quinto partido : por qué siempre decepciona",
          "category": "other",
          "source": "GDELT_DOC",
          "time": "2026-06-11T18:00:00Z",
          "url": "https://www.clarin.com/deportes/mexico-debuta-sudafrica-mundial-busca-romper-maldicion-quinto-partido-siempre-decepciona_0_4AxoNVOWIG.html",
          "lat": 50.08,
          "lon": 14.43,
          "source_file": "gdelt_crossborder.geojson"
        },
        "infrastructure": {
          "id": "cz-digital-prague-ixp",
          "name": "Prague Internet Exchange / NIX.CZ",
          "country": "Czechia",
          "city": "Prague",
          "category": "digital",
          "subtype": "internet_exchange",
          "criticality": 9.0,
          "operator": "NIX.CZ",
          "lat": 50.075,
          "lon": 14.438,
          "source_file": "infra_digital.json"
        }
      },
      {
        "id": "2e3f7ebb89fd654a",
        "level": "critical",
        "score": 88.57,
        "distance_km": 0.8,
        "event": {
          "id": "cd4c33af1c778fdd",
          "title": "EU could sleepwalk into conflict with Russia ex - German navy chief",
          "category": "other",
          "source": "GDELT_DOC",
          "time": "2026-06-11T18:00:00Z",
          "url": "http://www.philippinetimes.com/news/279117124/eu-could-sleepwalk-into-conflict-with-russia-ex-german-navy-chief",
          "lat": 50.08,
          "lon": 14.43,
          "source_file": "gdelt_crossborder.geojson"
        },
        "infrastructure": {
          "id": "cz-digital-prague-ixp",
          "name": "Prague Internet Exchange / NIX.CZ",
          "country": "Czechia",
          "city": "Prague",
          "category": "digital",
          "subtype": "internet_exchange",
          "criticality": 9.0,
          "operator": "NIX.CZ",
          "lat": 50.075,
          "lon": 14.438,
          "source_file": "infra_digital.json"
        }
      },
      {
        "id": "1a53b4ccefacc12f",
        "level": "critical",
        "score": 88.57,
        "distance_km": 0.8,
        "event": {
          "id": "e35c99afed80f853",
          "title": "Faggete Foresta Umbra verso il bis UNESCO",
          "category": "other",
          "source": "GDELT_DOC",
          "time": "2026-06-11T18:00:00Z",
          "url": "https://www.manfredonianews.it/2020/03/17/faggete-foresta-umbra-verso-il-bis-unesco/",
          "lat": 50.08,
          "lon": 14.43,
          "source_file": "gdelt_crossborder.geojson"
        },
        "infrastructure": {
          "id": "cz-digital-prague-ixp",
          "name": "Prague Internet Exchange / NIX.CZ",
          "country": "Czechia",
          "city": "Prague",
          "category": "digital",
          "subtype": "internet_exchange",
          "criticality": 9.0,
          "operator": "NIX.CZ",
          "lat": 50.075,
          "lon": 14.438,
          "source_file": "infra_digital.json"
        }
      }
    ]
  }
}